odoo/addons/fieldservice_survey/README.rst
odoo/addons/fieldservice_survey/__init__.py
odoo/addons/fieldservice_survey/__manifest__.py
odoo/addons/fieldservice_survey/controllers/__init__.py
odoo/addons/fieldservice_survey/controllers/main.py
odoo/addons/fieldservice_survey/data/fsm_order_survey_data.xml
odoo/addons/fieldservice_survey/data/mail_data.xml
odoo/addons/fieldservice_survey/i18n/fieldservice_survey.pot
odoo/addons/fieldservice_survey/i18n/it.po
odoo/addons/fieldservice_survey/models/__init__.py
odoo/addons/fieldservice_survey/models/fsm_order.py
odoo/addons/fieldservice_survey/models/res_company.py
odoo/addons/fieldservice_survey/models/res_config_settings.py
odoo/addons/fieldservice_survey/models/survey_survey.py
odoo/addons/fieldservice_survey/models/survey_user_input.py
odoo/addons/fieldservice_survey/readme/CONTRIBUTORS.rst
odoo/addons/fieldservice_survey/readme/DESCRIPTION.rst
odoo/addons/fieldservice_survey/readme/ROADMAP.rst
odoo/addons/fieldservice_survey/readme/USAGE.rst
odoo/addons/fieldservice_survey/security/ir.model.access.csv
odoo/addons/fieldservice_survey/security/res_groups.xml
odoo/addons/fieldservice_survey/static/description/icon.png
odoo/addons/fieldservice_survey/static/description/index.html
odoo/addons/fieldservice_survey/tests/__init__.py
odoo/addons/fieldservice_survey/tests/test_fsm_order.py
odoo/addons/fieldservice_survey/tests/test_fsm_order_survey_submit.py
odoo/addons/fieldservice_survey/views/fsm_order.xml
odoo/addons/fieldservice_survey/views/res_config_settings.xml
odoo/addons/fieldservice_survey/views/survey_survey.xml
odoo/addons/fieldservice_survey/views/survey_templates_statistics.xml
odoo/addons/fieldservice_survey/views/survey_user_input.xml
odoo/addons/fieldservice_survey/wizard/__init__.py
odoo/addons/fieldservice_survey/wizard/fsm_order_survey_submit.py
odoo/addons/fieldservice_survey/wizard/fsm_order_survey_submit.xml
odoo14_addon_fieldservice_survey-14.0.1.0.1.dev2.dist-info/METADATA
odoo14_addon_fieldservice_survey-14.0.1.0.1.dev2.dist-info/WHEEL
odoo14_addon_fieldservice_survey-14.0.1.0.1.dev2.dist-info/top_level.txt
odoo14_addon_fieldservice_survey-14.0.1.0.1.dev2.dist-info/RECORD
